openCDS/__init__.py
openCDS/main.py
opencds-0.0.3.dist-info/METADATA
opencds-0.0.3.dist-info/WHEEL
opencds-0.0.3.dist-info/entry_points.txt
opencds-0.0.3.dist-info/licenses/LICENSE
opencds-0.0.3.dist-info/RECORD
